grafit/__init__.py
grafit/cli.py
grafit/database.py
grafit/fit_analyzer.py
grafit/fit_importer.py
grafit/schema_generator.py
grafit-0.1.0.dist-info/METADATA
grafit-0.1.0.dist-info/WHEEL
grafit-0.1.0.dist-info/entry_points.txt
grafit-0.1.0.dist-info/top_level.txt
grafit-0.1.0.dist-info/RECORD
